{
  "id": "dependency-phase-2",
  "name": "Dependency Updates - Phase 2 (Next Sprint)",
  "status": "active",
  "objective": "Update fumadocs to latest, shiki to 4.x, React to 19.2.x, and zod to 4.3.x",
  "context_files": [],
  "reference_files": ["apps/docs/package.json", "package.json"],
  "exit_criteria": [
    "fumadocs packages updated to latest",
    "shiki updated to 4.x",
    "React updated to 19.2.x",
    "zod updated to 4.3.x",
    "All builds pass"
  ],
  "subtask_count": 5,
  "completed_count": 0,
  "created_at": "2026-03-18T00:00:00Z",
  "priority": "medium",
  "bounded_context": "infrastructure",
  "module": "@opentribe/monorepo",
  "release_slice": "Phase 2"
}
